c2cgeoportal_admin/__init__.py
c2cgeoportal_admin/py.typed
c2cgeoportal_admin/routes.py
c2cgeoportal_admin/subscribers.py
c2cgeoportal_admin/widgets.py
c2cgeoportal_admin/lib/__init__.py
c2cgeoportal_admin/lib/lingva_extractor.py
c2cgeoportal_admin/lib/ogcserver_synchronizer.py
c2cgeoportal_admin/schemas/__init__.py
c2cgeoportal_admin/schemas/dimensions.py
c2cgeoportal_admin/schemas/functionalities.py
c2cgeoportal_admin/schemas/interfaces.py
c2cgeoportal_admin/schemas/metadata.py
c2cgeoportal_admin/schemas/restriction_areas.py
c2cgeoportal_admin/schemas/roles.py
c2cgeoportal_admin/schemas/treegroup.py
c2cgeoportal_admin/schemas/treeitem.py
c2cgeoportal_admin/static/layertree.css
c2cgeoportal_admin/static/navbar.css
c2cgeoportal_admin/static/theme.css
c2cgeoportal_admin/templates/404.jinja2
c2cgeoportal_admin/templates/edit.jinja2
c2cgeoportal_admin/templates/home.jinja2
c2cgeoportal_admin/templates/index.jinja2
c2cgeoportal_admin/templates/layertree.jinja2
c2cgeoportal_admin/templates/layout.jinja2
c2cgeoportal_admin/templates/navigation_navbar.jinja2
c2cgeoportal_admin/templates/ogcserver_synchronize.jinja2
c2cgeoportal_admin/templates/widgets/child.pt
c2cgeoportal_admin/templates/widgets/children.pt
c2cgeoportal_admin/templates/widgets/dimension.pt
c2cgeoportal_admin/templates/widgets/dimensions.pt
c2cgeoportal_admin/templates/widgets/functionality_fields.pt
c2cgeoportal_admin/templates/widgets/layer_fields.pt
c2cgeoportal_admin/templates/widgets/layer_group_fields.pt
c2cgeoportal_admin/templates/widgets/layer_v1_fields.pt
c2cgeoportal_admin/templates/widgets/metadata.pt
c2cgeoportal_admin/templates/widgets/metadatas.pt
c2cgeoportal_admin/templates/widgets/ogcserver_fields.pt
c2cgeoportal_admin/templates/widgets/restriction_area_fields.pt
c2cgeoportal_admin/templates/widgets/role_fields.pt
c2cgeoportal_admin/templates/widgets/theme_fields.pt
c2cgeoportal_admin/templates/widgets/user_fields.pt
c2cgeoportal_admin/views/__init__.py
c2cgeoportal_admin-2.9.0.388.dist-info/METADATA
c2cgeoportal_admin-2.9.0.388.dist-info/WHEEL
c2cgeoportal_admin-2.9.0.388.dist-info/entry_points.txt
c2cgeoportal_admin-2.9.0.388.dist-info/top_level.txt
c2cgeoportal_admin-2.9.0.388.dist-info/RECORD
